{
	"info": {
		"_postman_id": "f7df2a6f-e7ba-4744-bedb-e59a7a55ebd9",
		"name": "SmartHelthcare-booking",
		"schema": "https://schema.getpostman.com/json/collection/v2.1.0/collection.json",
		"_exporter_id": "20035804"
	},
	"item": [
		{
			"name": "Register",
			"request": {
				"method": "POST",
				"header": [],
				"body": {
					"mode": "raw",
					"raw": "{\r\n    \"name\": \"Tushar\",\r\n    \"email\": \"Tushar@gmail.com\",\r\n    \"password\": \"Tushar@123\",\r\n    \"role\": \"patient\" \r\n}",
					"options": {
						"raw": {
							"language": "json"
						}
					}
				},
				"url": {
					"raw": "http://localhost:5000/api/v1/auth/register",
					"protocol": "http",
					"host": [
						"localhost"
					],
					"port": "5000",
					"path": [
						"api",
						"v1",
						"auth",
						"register"
					]
				}
			},
			"response": []
		},
		{
			"name": "Login",
			"request": {
				"method": "POST",
				"header": [],
				"body": {
					"mode": "raw",
					"raw": "{\r\n    \"email\": \"Tushar@gmail.com\",\r\n    \"password\" : \"Tushar@123\"\r\n}",
					"options": {
						"raw": {
							"language": "json"
						}
					}
				},
				"url": {
					"raw": "http://localhost:5000/api/v1/auth/login",
					"protocol": "http",
					"host": [
						"localhost"
					],
					"port": "5000",
					"path": [
						"api",
						"v1",
						"auth",
						"login"
					]
				}
			},
			"response": []
		},
		{
			"name": "get All User",
			"request": {
				"method": "GET",
				"header": [],
				"url": {
					"raw": "http://localhost:5000/api/v1/users",
					"protocol": "http",
					"host": [
						"localhost"
					],
					"port": "5000",
					"path": [
						"api",
						"v1",
						"users"
					]
				}
			},
			"response": []
		},
		{
			"name": "get Single User",
			"request": {
				"method": "GET",
				"header": [],
				"url": {
					"raw": "http://localhost:5000/api/v1/users/65a8d44357124b4f587e0400",
					"protocol": "http",
					"host": [
						"localhost"
					],
					"port": "5000",
					"path": [
						"api",
						"v1",
						"users",
						"65a8d44357124b4f587e0400"
					]
				}
			},
			"response": []
		},
		{
			"name": "Update User",
			"request": {
				"method": "PUT",
				"header": [],
				"body": {
					"mode": "raw",
					"raw": "{\r\n    \"role\":\"doctor\"\r\n}",
					"options": {
						"raw": {
							"language": "json"
						}
					}
				},
				"url": {
					"raw": "http://localhost:5000/api/v1/users/65a8d44357124b4f587e0400",
					"protocol": "http",
					"host": [
						"localhost"
					],
					"port": "5000",
					"path": [
						"api",
						"v1",
						"users",
						"65a8d44357124b4f587e0400"
					]
				}
			},
			"response": []
		},
		{
			"name": "User Delete",
			"request": {
				"method": "DELETE",
				"header": [],
				"url": {
					"raw": "http://localhost:5000/api/v1/users/65a8d44357124b4f587e0400",
					"protocol": "http",
					"host": [
						"localhost"
					],
					"port": "5000",
					"path": [
						"api",
						"v1",
						"users",
						"65a8d44357124b4f587e0400"
					]
				}
			},
			"response": []
		}
	]
}